[
    {
        "layout_dets": [
            {
                "category_id": 1,
                "poly": [
                    163.3241424560547,
                    1121.455078125,
                    968.3880004882812,
                    1121.455078125,
                    968.3880004882812,
                    1255.511474609375,
                    163.3241424560547,
                    1255.511474609375
                ],
                "score": 0.9999949336051941
            },
            {
                "category_id": 1,
                "poly": [
                    165.11903381347656,
                    750.3841552734375,
                    969.1611328125,
                    750.3841552734375,
                    969.1611328125,
                    950.8291015625,
                    165.11903381347656,
                    950.8291015625
                ],
                "score": 0.9999935030937195
            },
            {
                "category_id": 1,
                "poly": [
                    164.8243865966797,
                    952.9771118164062,
                    968.4236450195312,
                    952.9771118164062,
                    968.4236450195312,
                    1119.3699951171875,
                    164.8243865966797,
                    1119.3699951171875
                ],
                "score": 0.9999935030937195
            },
            {
                "category_id": 1,
                "poly": [
                    167.14512634277344,
                    551.7304077148438,
                    967.9445190429688,
                    551.7304077148438,
                    967.9445190429688,
                    618.5252685546875,
                    167.14512634277344,
                    618.5252685546875
                ],
                "score": 0.9999908804893494
            },
            {
                "category_id": 1,
                "poly": [
                    166.23060607910156,
                    647.9536743164062,
                    968.1135864257812,
                    647.9536743164062,
                    968.1135864257812,
                    747.7052001953125,
                    166.23060607910156,
                    747.7052001953125
                ],
                "score": 0.9999884366989136
            },
            {
                "category_id": 1,
                "poly": [
                    168.60537719726562,
                    485.9285888671875,
                    965.8603515625,
                    485.9285888671875,
                    965.8603515625,
                    535.3073120117188,
                    168.60537719726562,
                    535.3073120117188
                ],
                "score": 0.9999510645866394
            },
            {
                "category_id": 2,
                "poly": [
                    6.6231184005737305,
                    1719.6583251953125,
                    1132.31201171875,
                    1719.6583251953125,
                    1132.31201171875,
                    1746.4708251953125,
                    6.6231184005737305,
                    1746.4708251953125
                ],
                "score": 0.9998579025268555
            },
            {
                "category_id": 2,
                "poly": [
                    563.7369995117188,
                    1547.59130859375,
                    576.4518432617188,
                    1547.59130859375,
                    576.4518432617188,
                    1565.92822265625,
                    563.7369995117188,
                    1565.92822265625
                ],
                "score": 0.999222457408905
            },
            {
                "category_id": 1,
                "poly": [
                    215.21859741210938,
                    1268.0086669921875,
                    667.7198486328125,
                    1268.0086669921875,
                    667.7198486328125,
                    1297.28271484375,
                    215.21859741210938,
                    1297.28271484375
                ],
                "score": 0.9983630180358887
            },
            {
                "category_id": 0,
                "poly": [
                    167.24215698242188,
                    225.09130859375,
                    967.6204223632812,
                    225.09130859375,
                    967.6204223632812,
                    365.24017333984375,
                    167.24215698242188,
                    365.24017333984375
                ],
                "score": 0.9276456832885742
            },
            {
                "category_id": 1,
                "poly": [
                    547.39208984375,
                    400.48583984375,
                    583.82373046875,
                    400.48583984375,
                    583.82373046875,
                    429.1102294921875,
                    547.39208984375,
                    429.1102294921875
                ],
                "score": 0.6155694127082825
            },
            {
                "category_id": 8,
                "poly": [
                    472.4332580566406,
                    438.5267028808594,
                    656.1065673828125,
                    438.5267028808594,
                    656.1065673828125,
                    471.699951171875,
                    472.4332580566406,
                    471.699951171875
                ],
                "score": 0.571371853351593
            },
            {
                "category_id": 1,
                "poly": [
                    472.8157958984375,
                    438.8794250488281,
                    656.0949096679688,
                    438.8794250488281,
                    656.0949096679688,
                    471.7407531738281,
                    472.8157958984375,
                    471.7407531738281
                ],
                "score": 0.4742524027824402
            },
            {
                "category_id": 0,
                "poly": [
                    547.4320678710938,
                    400.5037536621094,
                    583.80078125,
                    400.5037536621094,
                    583.80078125,
                    429.0599060058594,
                    547.4320678710938,
                    429.0599060058594
                ],
                "score": 0.45969995856285095
            },
            {
                "category_id": 0,
                "poly": [
                    472.43572998046875,
                    438.5153503417969,
                    656.0902099609375,
                    438.5153503417969,
                    656.0902099609375,
                    471.7337951660156,
                    472.43572998046875,
                    471.7337951660156
                ],
                "score": 0.31348881125450134
            },
            {
                "category_id": 13,
                "poly": [
                    317,
                    1019,
                    392,
                    1019,
                    392,
                    1051,
                    317,
                    1051
                ],
                "score": 0.6,
                "latex": "16\\,\\mathrm{~kc~}"
            },
            {
                "category_id": 13,
                "poly": [
                    360,
                    783,
                    453,
                    783,
                    453,
                    815,
                    360,
                    815
                ],
                "score": 0.58,
                "latex": "16.2~\\mathrm{kc}."
            },
            {
                "category_id": 13,
                "poly": [
                    798,
                    331,
                    872,
                    331,
                    872,
                    363,
                    798,
                    363
                ],
                "score": 0.37,
                "latex": "1923^{*}"
            },
            {
                "category_id": 13,
                "poly": [
                    259,
                    783,
                    317,
                    783,
                    317,
                    816,
                    259,
                    816
                ],
                "score": 0.35,
                "latex": "\\left(\\ker.\\right)"
            },
            {
                "category_id": 15,
                "poly": [
                    206.0,
                    1121.0,
                    968.0,
                    1121.0,
                    968.0,
                    1157.0,
                    206.0,
                    1157.0
                ],
                "score": 1.0,
                "text": "The signal strength of Nauen, both in the morning and during"
            },
            {
                "category_id": 15,
                "poly": [
                    163.0,
                    1155.0,
                    968.0,
                    1155.0,
                    968.0,
                    1192.0,
                    163.0,
                    1192.0
                ],
                "score": 0.98,
                "text": "the afternoon fading, is practically the same as in the correspond-"
            },
            {
                "category_id": 15,
                "poly": [
                    162.0,
                    1189.0,
                    969.0,
                    1189.0,
                    969.0,
                    1227.0,
                    162.0,
                    1227.0
                ],
                "score": 0.99,
                "text": "ing months last year. The atmospheric disturbances are con-"
            },
            {
                "category_id": 15,
                "poly": [
                    164.0,
                    1226.0,
                    537.0,
                    1226.0,
                    537.0,
                    1259.0,
                    164.0,
                    1259.0
                ],
                "score": 1.0,
                "text": "siderably lighter than in 1922."
            },
            {
                "category_id": 15,
                "poly": [
                    207.0,
                    750.0,
                    969.0,
                    750.0,
                    969.0,
                    784.0,
                    207.0,
                    784.0
                ],
                "score": 0.97,
                "text": "Lafayette's change of frequency from 12.8 kilocycles per"
            },
            {
                "category_id": 15,
                "poly": [
                    164.0,
                    786.0,
                    258.0,
                    786.0,
                    258.0,
                    819.0,
                    164.0,
                    819.0
                ],
                "score": 1.0,
                "text": "second"
            },
            {
                "category_id": 15,
                "poly": [
                    318.0,
                    786.0,
                    359.0,
                    786.0,
                    359.0,
                    819.0,
                    318.0,
                    819.0
                ],
                "score": 0.96,
                "text": "to"
            },
            {
                "category_id": 15,
                "poly": [
                    454.0,
                    786.0,
                    969.0,
                    786.0,
                    969.0,
                    819.0,
                    454.0,
                    819.0
                ],
                "score": 0.98,
                "text": ", mentioned in the May-June report, has"
            },
            {
                "category_id": 15,
                "poly": [
                    163.0,
                    819.0,
                    971.0,
                    819.0,
                    971.0,
                    854.0,
                    163.0,
                    854.0
                ],
                "score": 0.98,
                "text": "been accompanied by an increase in signal strength in Washing-"
            },
            {
                "category_id": 15,
                "poly": [
                    165.0,
                    853.0,
                    971.0,
                    853.0,
                    971.0,
                    885.0,
                    165.0,
                    885.0
                ],
                "score": 0.98,
                "text": "ton of about 1.6 times. As far as is known, there have been no"
            },
            {
                "category_id": 15,
                "poly": [
                    163.0,
                    884.0,
                    971.0,
                    884.0,
                    971.0,
                    922.0,
                    163.0,
                    922.0
                ],
                "score": 0.99,
                "text": "changes other than the change in frequency to explain the"
            },
            {
                "category_id": 15,
                "poly": [
                    164.0,
                    921.0,
                    275.0,
                    921.0,
                    275.0,
                    954.0,
                    164.0,
                    954.0
                ],
                "score": 0.99,
                "text": "increase."
            },
            {
                "category_id": 15,
                "poly": [
                    207.0,
                    951.0,
                    967.0,
                    951.0,
                    967.0,
                    989.0,
                    207.0,
                    989.0
                ],
                "score": 0.99,
                "text": "This, together with some observations on shorter wave sta-"
            },
            {
                "category_id": 15,
                "poly": [
                    163.0,
                    986.0,
                    966.0,
                    986.0,
                    966.0,
                    1022.0,
                    163.0,
                    1022.0
                ],
                "score": 1.0,
                "text": "tions, may indicate a distinct optimum frequency in the neigh-"
            },
            {
                "category_id": 15,
                "poly": [
                    164.0,
                    1021.0,
                    316.0,
                    1021.0,
                    316.0,
                    1053.0,
                    164.0,
                    1053.0
                ],
                "score": 1.0,
                "text": "borhoodof"
            },
            {
                "category_id": 15,
                "poly": [
                    393.0,
                    1021.0,
                    966.0,
                    1021.0,
                    966.0,
                    1053.0,
                    393.0,
                    1053.0
                ],
                "score": 0.98,
                "text": ".for northern trans-Atlantic communication,"
            },
            {
                "category_id": 15,
                "poly": [
                    162.0,
                    1053.0,
                    970.0,
                    1053.0,
                    970.0,
                    1089.0,
                    162.0,
                    1089.0
                ],
                "score": 0.99,
                "text": "but of course it is still too early to draw definite conclusions on"
            },
            {
                "category_id": 15,
                "poly": [
                    163.0,
                    1087.0,
                    299.0,
                    1087.0,
                    299.0,
                    1123.0,
                    163.0,
                    1123.0
                ],
                "score": 0.99,
                "text": "this point."
            },
            {
                "category_id": 15,
                "poly": [
                    167.0,
                    553.0,
                    966.0,
                    553.0,
                    966.0,
                    586.0,
                    167.0,
                    586.0
                ],
                "score": 0.98,
                "text": "(Communication from the International Union of Scientific Radio"
            },
            {
                "category_id": 15,
                "poly": [
                    494.0,
                    584.0,
                    640.0,
                    584.0,
                    640.0,
                    623.0,
                    494.0,
                    623.0
                ],
                "score": 1.0,
                "text": "Telegraphy)"
            },
            {
                "category_id": 15,
                "poly": [
                    207.0,
                    646.0,
                    968.0,
                    646.0,
                    968.0,
                    685.0,
                    207.0,
                    685.0
                ],
                "score": 1.0,
                "text": "The observations for July and August afford some opportu-"
            },
            {
                "category_id": 15,
                "poly": [
                    164.0,
                    681.0,
                    968.0,
                    681.0,
                    968.0,
                    716.0,
                    164.0,
                    716.0
                ],
                "score": 1.0,
                "text": "nities for a comparison of thissummer's result with the correspond-"
            },
            {
                "category_id": 15,
                "poly": [
                    165.0,
                    718.0,
                    453.0,
                    718.0,
                    453.0,
                    750.0,
                    165.0,
                    750.0
                ],
                "score": 0.99,
                "text": "ing values of last year."
            },
            {
                "category_id": 15,
                "poly": [
                    167.0,
                    486.0,
                    968.0,
                    486.0,
                    968.0,
                    516.0,
                    167.0,
                    516.0
                ],
                "score": 0.96,
                "text": "(CHIEF OF THE RADIO PHYSICAL LABORATORY, BUREAU OF STANDARDS,"
            },
            {
                "category_id": 15,
                "poly": [
                    453.0,
                    510.0,
                    683.0,
                    510.0,
                    683.0,
                    536.0,
                    453.0,
                    536.0
                ],
                "score": 0.99,
                "text": "WASHINGTON,D.C.)"
            },
            {
                "category_id": 15,
                "poly": [
                    2.0,
                    1722.0,
                    1136.0,
                    1722.0,
                    1136.0,
                    1751.0,
                    2.0,
                    1751.0
                ],
                "score": 0.99,
                "text": "ed licensed use limited to: Everything Demo User. Downloaded on January 11,2024 at 15:55:37 UTC from IEEE Xplore. Restriction"
            },
            {
                "category_id": 15,
                "poly": [
                    562.0,
                    1548.0,
                    579.0,
                    1548.0,
                    579.0,
                    1572.0,
                    562.0,
                    1572.0
                ],
                "score": 1.0,
                "text": "3"
            },
            {
                "category_id": 15,
                "poly": [
                    214.0,
                    1267.0,
                    666.0,
                    1267.0,
                    666.0,
                    1301.0,
                    214.0,
                    1301.0
                ],
                "score": 0.99,
                "text": "*Received by the Editor, November 3, 1923"
            },
            {
                "category_id": 15,
                "poly": [
                    165.0,
                    231.0,
                    966.0,
                    231.0,
                    966.0,
                    260.0,
                    165.0,
                    260.0
                ],
                "score": 0.99,
                "text": "RECEIVING MEASUREMENTSANDATMOSPHERIC"
            },
            {
                "category_id": 15,
                "poly": [
                    222.0,
                    266.0,
                    911.0,
                    266.0,
                    911.0,
                    295.0,
                    222.0,
                    295.0
                ],
                "score": 0.96,
                "text": "DISTURBANCES AT THE RADIO PHYSICAL"
            },
            {
                "category_id": 15,
                "poly": [
                    250.0,
                    301.0,
                    880.0,
                    301.0,
                    880.0,
                    330.0,
                    250.0,
                    330.0
                ],
                "score": 0.97,
                "text": "LABORATORY, BUREAU OF STANDARDS,"
            },
            {
                "category_id": 15,
                "poly": [
                    265.0,
                    333.0,
                    797.0,
                    333.0,
                    797.0,
                    362.0,
                    265.0,
                    362.0
                ],
                "score": 0.98,
                "text": "WASHINGTON, JULY AND AUGUST,"
            },
            {
                "category_id": 15,
                "poly": [
                    543.0,
                    400.0,
                    588.0,
                    400.0,
                    588.0,
                    435.0,
                    543.0,
                    435.0
                ],
                "score": 0.78,
                "text": "BY"
            },
            {
                "category_id": 15,
                "poly": [
                    469.0,
                    438.0,
                    658.0,
                    438.0,
                    658.0,
                    472.0,
                    469.0,
                    472.0
                ],
                "score": 0.99,
                "text": "L. W. AUSTIN"
            },
            {
                "category_id": 15,
                "poly": [
                    543.0,
                    400.0,
                    588.0,
                    400.0,
                    588.0,
                    435.0,
                    543.0,
                    435.0
                ],
                "score": 0.78,
                "text": "BY"
            },
            {
                "category_id": 15,
                "poly": [
                    469.0,
                    438.0,
                    658.0,
                    438.0,
                    658.0,
                    472.0,
                    469.0,
                    472.0
                ],
                "score": 0.99,
                "text": "L. W. AUSTIN"
            }
        ],
        "page_info": {
            "page_no": 0,
            "height": 1800,
            "width": 1134
        }
    },
    {
        "layout_dets": [
            {
                "category_id": 7,
                "poly": [
                    208.02394104003906,
                    1390.958740234375,
                    403.3337707519531,
                    1390.958740234375,
                    403.3337707519531,
                    1488.279541015625,
                    208.02394104003906,
                    1488.279541015625
                ],
                "score": 0.9999983310699463
            },
            {
                "category_id": 5,
                "poly": [
                    170.01669311523438,
                    295.911865234375,
                    972.9564819335938,
                    295.911865234375,
                    972.9564819335938,
                    1386.3778076171875,
                    170.01669311523438,
                    1386.3778076171875
                ],
                "score": 0.9999727010726929
            },
            {
                "category_id": 2,
                "poly": [
                    6.04587459564209,
                    1718.6839599609375,
                    1134.0,
                    1718.6839599609375,
                    1134.0,
                    1747.029296875,
                    6.04587459564209,
                    1747.029296875
                ],
                "score": 0.9999557733535767
            },
            {
                "category_id": 2,
                "poly": [
                    557.5421142578125,
                    1596.4261474609375,
                    573.0545043945312,
                    1596.4261474609375,
                    573.0545043945312,
                    1614.9755859375,
                    557.5421142578125,
                    1614.9755859375
                ],
                "score": 0.9998753070831299
            },
            {
                "category_id": 1,
                "poly": [
                    171.43690490722656,
                    183.0657501220703,
                    978.751953125,
                    183.0657501220703,
                    978.751953125,
                    282.11083984375,
                    171.43690490722656,
                    282.11083984375
                ],
                "score": 0.9436003565788269
            },
            {
                "category_id": 6,
                "poly": [
                    171.3392791748047,
                    182.86984252929688,
                    978.0225830078125,
                    182.86984252929688,
                    978.0225830078125,
                    281.76910400390625,
                    171.3392791748047,
                    281.76910400390625
                ],
                "score": 0.2081868052482605
            },
            {
                "category_id": 13,
                "poly": [
                    341,
                    216,
                    508,
                    216,
                    508,
                    249,
                    341,
                    249
                ],
                "score": 0.8,
                "latex": "\\lambda\\!\\!=\\!12,\\!800\\ \\mathrm{~m}."
            },
            {
                "category_id": 13,
                "poly": [
                    175,
                    216,
                    276,
                    216,
                    276,
                    250,
                    175,
                    250
                ],
                "score": 0.79,
                "latex": "(f\\!=\\!23.4"
            },
            {
                "category_id": 13,
                "poly": [
                    210,
                    1423,
                    289,
                    1423,
                    289,
                    1453,
                    210,
                    1453
                ],
                "score": 0.66,
                "latex": "^{\\ast\\ast}\\mathrm{Not}"
            },
            {
                "category_id": 15,
                "poly": [
                    223.0,
                    1384.0,
                    383.0,
                    1384.0,
                    383.0,
                    1425.0,
                    223.0,
                    1425.0
                ],
                "score": 1.0,
                "text": "*Not heard."
            },
            {
                "category_id": 15,
                "poly": [
                    219.0,
                    1453.0,
                    399.0,
                    1453.0,
                    399.0,
                    1490.0,
                    219.0,
                    1490.0
                ],
                "score": 0.98,
                "text": "...Not taken."
            },
            {
                "category_id": 15,
                "poly": [
                    210.0,
                    1421.5,
                    402.0,
                    1421.5,
                    402.0,
                    1455.5,
                    210.0,
                    1455.5
                ],
                "score": 1.0,
                "text": "**Not sending."
            },
            {
                "category_id": 15,
                "poly": [
                    1.0,
                    1722.0,
                    1138.0,
                    1722.0,
                    1138.0,
                    1751.0,
                    1.0,
                    1751.0
                ],
                "score": 1.0,
                "text": "d licensed use limited to: Everything Demo User. Downloaded on January 11,2024 at 15:55:37 UTC from IEEE Xplore. Restriction:"
            },
            {
                "category_id": 15,
                "poly": [
                    559.0,
                    1599.0,
                    572.0,
                    1599.0,
                    572.0,
                    1616.0,
                    559.0,
                    1616.0
                ],
                "score": 1.0,
                "text": "4"
            },
            {
                "category_id": 15,
                "poly": [
                    235.0,
                    183.0,
                    910.0,
                    183.0,
                    910.0,
                    217.0,
                    235.0,
                    217.0
                ],
                "score": 0.97,
                "text": "FIELD INTENSITY OF NAUEN AND OF DISTURBANCES"
            },
            {
                "category_id": 15,
                "poly": [
                    277.0,
                    216.0,
                    340.0,
                    216.0,
                    340.0,
                    251.0,
                    277.0,
                    251.0
                ],
                "score": 0.8,
                "text": "kc."
            },
            {
                "category_id": 15,
                "poly": [
                    509.0,
                    216.0,
                    975.0,
                    216.0,
                    975.0,
                    251.0,
                    509.0,
                    251.0
                ],
                "score": 0.93,
                "text": ")IN JULY, 1923, IN M1CRO-VOLTS"
            },
            {
                "category_id": 15,
                "poly": [
                    494.0,
                    253.0,
                    651.0,
                    253.0,
                    651.0,
                    283.0,
                    494.0,
                    283.0
                ],
                "score": 1.0,
                "text": "PERMETER"
            },
            {
                "category_id": 15,
                "poly": [
                    234.0,
                    183.0,
                    910.0,
                    183.0,
                    910.0,
                    218.0,
                    234.0,
                    218.0
                ],
                "score": 0.98,
                "text": "FIELD INTENSITY OF NAUEN AND OF DISTURBANCES"
            },
            {
                "category_id": 15,
                "poly": [
                    277.0,
                    217.0,
                    340.0,
                    217.0,
                    340.0,
                    252.0,
                    277.0,
                    252.0
                ],
                "score": 0.8,
                "text": "kc。"
            },
            {
                "category_id": 15,
                "poly": [
                    509.0,
                    217.0,
                    976.0,
                    217.0,
                    976.0,
                    252.0,
                    509.0,
                    252.0
                ],
                "score": 0.93,
                "text": ")IN JULY, 1923, IN M1CRO-VOLTS"
            },
            {
                "category_id": 15,
                "poly": [
                    494.0,
                    253.0,
                    650.0,
                    253.0,
                    650.0,
                    283.0,
                    494.0,
                    283.0
                ],
                "score": 1.0,
                "text": "PERMETER"
            }
        ],
        "page_info": {
            "page_no": 1,
            "height": 1800,
            "width": 1134
        }
    },
    {
        "layout_dets": [
            {
                "category_id": 7,
                "poly": [
                    204.4830322265625,
                    1389.0313720703125,
                    399.27105712890625,
                    1389.0313720703125,
                    399.27105712890625,
                    1487.52294921875,
                    204.4830322265625,
                    1487.52294921875
                ],
                "score": 0.9999992251396179
            },
            {
                "category_id": 5,
                "poly": [
                    163.43612670898438,
                    293.7862243652344,
                    971.4121704101562,
                    293.7862243652344,
                    971.4121704101562,
                    1385.5262451171875,
                    163.43612670898438,
                    1385.5262451171875
                ],
                "score": 0.9999777674674988
            },
            {
                "category_id": 2,
                "poly": [
                    6.486204624176025,
                    1718.83203125,
                    1134.0,
                    1718.83203125,
                    1134.0,
                    1746.818603515625,
                    6.486204624176025,
                    1746.818603515625
                ],
                "score": 0.9999628067016602
            },
            {
                "category_id": 2,
                "poly": [
                    559.1082763671875,
                    1594.3262939453125,
                    574.5258178710938,
                    1594.3262939453125,
                    574.5258178710938,
                    1612.7061767578125,
                    559.1082763671875,
                    1612.7061767578125
                ],
                "score": 0.9998995065689087
            },
            {
                "category_id": 1,
                "poly": [
                    164.47230529785156,
                    181.11326599121094,
                    976.2901000976562,
                    181.11326599121094,
                    976.2901000976562,
                    280.2431640625,
                    164.47230529785156,
                    280.2431640625
                ],
                "score": 0.9732992053031921
            },
            {
                "category_id": 13,
                "poly": [
                    331,
                    215,
                    500,
                    215,
                    500,
                    248,
                    331,
                    248
                ],
                "score": 0.85,
                "latex": "\\dot{\\lambda}\\!=\\!18,\\!900\\,\\mathrm{~m.~}"
            },
            {
                "category_id": 13,
                "poly": [
                    169,
                    215,
                    269,
                    215,
                    269,
                    249,
                    169,
                    249
                ],
                "score": 0.84,
                "latex": "(f\\!=\\!15.9"
            },
            {
                "category_id": 13,
                "poly": [
                    205,
                    1421,
                    285,
                    1421,
                    285,
                    1452,
                    205,
                    1452
                ],
                "score": 0.44,
                "latex": "\\mathrm{**Not}"
            },
            {
                "category_id": 15,
                "poly": [
                    220.0,
                    1383.0,
                    378.0,
                    1383.0,
                    378.0,
                    1423.0,
                    220.0,
                    1423.0
                ],
                "score": 1.0,
                "text": "*Not heard."
            },
            {
                "category_id": 15,
                "poly": [
                    286.0,
                    1417.0,
                    398.0,
                    1417.0,
                    398.0,
                    1457.0,
                    286.0,
                    1457.0
                ],
                "score": 0.97,
                "text": " sending."
            },
            {
                "category_id": 15,
                "poly": [
                    212.0,
                    1452.0,
                    395.0,
                    1452.0,
                    395.0,
                    1489.0,
                    212.0,
                    1489.0
                ],
                "score": 0.96,
                "text": ".. .Not taken."
            },
            {
                "category_id": 15,
                "poly": [
                    1.0,
                    1720.0,
                    1138.0,
                    1720.0,
                    1138.0,
                    1751.0,
                    1.0,
                    1751.0
                ],
                "score": 0.99,
                "text": "d licensed use limited to: Everything Demo User. Downloaded on January 11,2024 at 15:55:37 UTC from IEEE Xplore. Restriction:"
            },
            {
                "category_id": 15,
                "poly": [
                    560.0,
                    1597.0,
                    574.0,
                    1597.0,
                    574.0,
                    1617.0,
                    560.0,
                    1617.0
                ],
                "score": 0.89,
                "text": "5"
            },
            {
                "category_id": 15,
                "poly": [
                    205.0,
                    184.0,
                    931.0,
                    184.0,
                    931.0,
                    213.0,
                    205.0,
                    213.0
                ],
                "score": 0.96,
                "text": "FIELD INTENSITY OF LAFAYETTE AND OF DISTURBANCES"
            },
            {
                "category_id": 15,
                "poly": [
                    270.0,
                    218.0,
                    330.0,
                    218.0,
                    330.0,
                    250.0,
                    270.0,
                    250.0
                ],
                "score": 0.8,
                "text": "Kc。"
            },
            {
                "category_id": 15,
                "poly": [
                    501.0,
                    218.0,
                    972.0,
                    218.0,
                    972.0,
                    250.0,
                    501.0,
                    250.0
                ],
                "score": 0.92,
                "text": ")IN JULY,1923, IN M1CRO-VOLTS"
            },
            {
                "category_id": 15,
                "poly": [
                    490.0,
                    252.0,
                    647.0,
                    252.0,
                    647.0,
                    282.0,
                    490.0,
                    282.0
                ],
                "score": 1.0,
                "text": "PERMETER"
            }
        ],
        "page_info": {
            "page_no": 2,
            "height": 1800,
            "width": 1134
        }
    },
    {
        "layout_dets": [
            {
                "category_id": 7,
                "poly": [
                    214.1507110595703,
                    1367.6683349609375,
                    404.318359375,
                    1367.6683349609375,
                    404.318359375,
                    1465.2066650390625,
                    214.1507110595703,
                    1465.2066650390625
                ],
                "score": 0.9999979734420776
            },
            {
                "category_id": 5,
                "poly": [
                    166.53271484375,
                    305.3746032714844,
                    971.174560546875,
                    305.3746032714844,
                    971.174560546875,
                    1363.019775390625,
                    166.53271484375,
                    1363.019775390625
                ],
                "score": 0.9999756813049316
            },
            {
                "category_id": 2,
                "poly": [
                    7.174147129058838,
                    1718.9046630859375,
                    1134.0,
                    1718.9046630859375,
                    1134.0,
                    1746.7314453125,
                    7.174147129058838,
                    1746.7314453125
                ],
                "score": 0.9999665021896362
            },
            {
                "category_id": 2,
                "poly": [
                    565.1558227539062,
                    1587.0919189453125,
                    581.4360961914062,
                    1587.0919189453125,
                    581.4360961914062,
                    1606.7552490234375,
                    565.1558227539062,
                    1606.7552490234375
                ],
                "score": 0.9999090433120728
            },
            {
                "category_id": 1,
                "poly": [
                    166.2880859375,
                    192.96669006347656,
                    974.04541015625,
                    192.96669006347656,
                    974.04541015625,
                    290.4377746582031,
                    166.2880859375,
                    290.4377746582031
                ],
                "score": 0.8566550612449646
            },
            {
                "category_id": 6,
                "poly": [
                    166.29168701171875,
                    192.8958282470703,
                    974.0198364257812,
                    192.8958282470703,
                    974.0198364257812,
                    290.4355773925781,
                    166.29168701171875,
                    290.4355773925781
                ],
                "score": 0.40747469663619995
            },
            {
                "category_id": 13,
                "poly": [
                    334,
                    227,
                    493,
                    227,
                    493,
                    259,
                    334,
                    259
                ],
                "score": 0.86,
                "latex": "\\lambda\\!=\\!12,\\!800\\,\\mathrm{~m~}"
            },
            {
                "category_id": 13,
                "poly": [
                    170,
                    227,
                    269,
                    227,
                    269,
                    262,
                    170,
                    262
                ],
                "score": 0.62,
                "latex": "(f\\!=\\!23.4"
            },
            {
                "category_id": 13,
                "poly": [
                    211,
                    1400,
                    291,
                    1400,
                    291,
                    1431,
                    211,
                    1431
                ],
                "score": 0.51,
                "latex": "**\\mathrm{Not}"
            },
            {
                "category_id": 15,
                "poly": [
                    224.0,
                    1364.0,
                    383.0,
                    1364.0,
                    383.0,
                    1397.0,
                    224.0,
                    1397.0
                ],
                "score": 1.0,
                "text": "*Not heard."
            },
            {
                "category_id": 15,
                "poly": [
                    292.0,
                    1395.0,
                    404.0,
                    1395.0,
                    404.0,
                    1436.0,
                    292.0,
                    1436.0
                ],
                "score": 0.98,
                "text": " sending."
            },
            {
                "category_id": 15,
                "poly": [
                    232.0,
                    1436.0,
                    399.0,
                    1436.0,
                    399.0,
                    1462.0,
                    232.0,
                    1462.0
                ],
                "score": 1.0,
                "text": "..Not taken."
            },
            {
                "category_id": 15,
                "poly": [
                    0.0,
                    1720.0,
                    1138.0,
                    1720.0,
                    1138.0,
                    1751.0,
                    0.0,
                    1751.0
                ],
                "score": 0.99,
                "text": "d licensed use limited to: Everything Demo User. Downloaded on January 11,2024 at 15:55:37 UTC from IEEE Xplore. Restriction:"
            },
            {
                "category_id": 15,
                "poly": [
                    566.0,
                    1589.0,
                    582.0,
                    1589.0,
                    582.0,
                    1612.0,
                    566.0,
                    1612.0
                ],
                "score": 1.0,
                "text": "6"
            },
            {
                "category_id": 15,
                "poly": [
                    231.0,
                    195.0,
                    904.0,
                    195.0,
                    904.0,
                    227.0,
                    231.0,
                    227.0
                ],
                "score": 0.97,
                "text": "FIELD INTENSITY OF NAUEN AND OF DISTURBANCES"
            },
            {
                "category_id": 15,
                "poly": [
                    270.0,
                    228.0,
                    333.0,
                    228.0,
                    333.0,
                    262.0,
                    270.0,
                    262.0
                ],
                "score": 0.73,
                "text": "kc.,"
            },
            {
                "category_id": 15,
                "poly": [
                    494.0,
                    228.0,
                    970.0,
                    228.0,
                    970.0,
                    262.0,
                    494.0,
                    262.0
                ],
                "score": 0.92,
                "text": ".）IN AUGUST,1923, IN M1CRO-VOLTS"
            },
            {
                "category_id": 15,
                "poly": [
                    490.0,
                    264.0,
                    646.0,
                    264.0,
                    646.0,
                    294.0,
                    490.0,
                    294.0
                ],
                "score": 1.0,
                "text": "PERMETER"
            },
            {
                "category_id": 15,
                "poly": [
                    231.0,
                    195.0,
                    904.0,
                    195.0,
                    904.0,
                    227.0,
                    231.0,
                    227.0
                ],
                "score": 0.97,
                "text": "FIELD INTENSITY OF NAUEN AND OF DISTURBANCES"
            },
            {
                "category_id": 15,
                "poly": [
                    270.0,
                    228.0,
                    333.0,
                    228.0,
                    333.0,
                    262.0,
                    270.0,
                    262.0
                ],
                "score": 0.73,
                "text": "kc.,"
            },
            {
                "category_id": 15,
                "poly": [
                    494.0,
                    228.0,
                    970.0,
                    228.0,
                    970.0,
                    262.0,
                    494.0,
                    262.0
                ],
                "score": 0.92,
                "text": ".）IN AUGUST,1923, IN M1CRO-VOLTS"
            },
            {
                "category_id": 15,
                "poly": [
                    490.0,
                    264.0,
                    646.0,
                    264.0,
                    646.0,
                    294.0,
                    490.0,
                    294.0
                ],
                "score": 1.0,
                "text": "PERMETER"
            }
        ],
        "page_info": {
            "page_no": 3,
            "height": 1800,
            "width": 1134
        }
    },
    {
        "layout_dets": [
            {
                "category_id": 7,
                "poly": [
                    207.2964630126953,
                    1329.416259765625,
                    398.40576171875,
                    1329.416259765625,
                    398.40576171875,
                    1426.08984375,
                    207.2964630126953,
                    1426.08984375
                ],
                "score": 0.9999989867210388
            },
            {
                "category_id": 5,
                "poly": [
                    162.1438751220703,
                    305.5636291503906,
                    972.7376098632812,
                    305.5636291503906,
                    972.7376098632812,
                    1333.0115966796875,
                    162.1438751220703,
                    1333.0115966796875
                ],
                "score": 0.9999772906303406
            },
            {
                "category_id": 2,
                "poly": [
                    7.590035915374756,
                    1719.12841796875,
                    1134.0,
                    1719.12841796875,
                    1134.0,
                    1746.4031982421875,
                    7.590035915374756,
                    1746.4031982421875
                ],
                "score": 0.9999688863754272
            },
            {
                "category_id": 2,
                "poly": [
                    556.3612670898438,
                    1594.7803955078125,
                    570.5277709960938,
                    1594.7803955078125,
                    570.5277709960938,
                    1612.056884765625,
                    556.3612670898438,
                    1612.056884765625
                ],
                "score": 0.9984532594680786
            },
            {
                "category_id": 1,
                "poly": [
                    162.94544982910156,
                    192.7210235595703,
                    973.56591796875,
                    192.7210235595703,
                    973.56591796875,
                    277.4143371582031,
                    162.94544982910156,
                    277.4143371582031
                ],
                "score": 0.9934408664703369
            },
            {
                "category_id": 6,
                "poly": [
                    486.41998291015625,
                    262.5382995605469,
                    644.91796875,
                    262.5382995605469,
                    644.91796875,
                    291.4178466796875,
                    486.41998291015625,
                    291.4178466796875
                ],
                "score": 0.955830991268158
            },
            {
                "category_id": 6,
                "poly": [
                    163.3419189453125,
                    192.3477325439453,
                    974.0850219726562,
                    192.3477325439453,
                    974.0850219726562,
                    281.70550537109375,
                    163.3419189453125,
                    281.70550537109375
                ],
                "score": 0.2804795503616333
            },
            {
                "category_id": 13,
                "poly": [
                    330,
                    226,
                    492,
                    226,
                    492,
                    259,
                    330,
                    259
                ],
                "score": 0.87,
                "latex": "\\dot{\\lambda}\\!=\\!18,\\!900\\,\\mathrm{~m~}"
            },
            {
                "category_id": 13,
                "poly": [
                    166,
                    225,
                    308,
                    225,
                    308,
                    259,
                    166,
                    259
                ],
                "score": 0.76,
                "latex": "(f\\!=\\!15.9\\,\\mathrm{~kc}"
            },
            {
                "category_id": 13,
                "poly": [
                    204,
                    1359,
                    285,
                    1359,
                    285,
                    1391,
                    204,
                    1391
                ],
                "score": 0.45,
                "latex": "^{\\ast\\ast}\\mathrm{Not}"
            },
            {
                "category_id": 15,
                "poly": [
                    219.0,
                    1322.0,
                    378.0,
                    1322.0,
                    378.0,
                    1361.0,
                    219.0,
                    1361.0
                ],
                "score": 1.0,
                "text": "*Not heard."
            },
            {
                "category_id": 15,
                "poly": [
                    286.0,
                    1353.0,
                    397.0,
                    1353.0,
                    397.0,
                    1397.0,
                    286.0,
                    1397.0
                ],
                "score": 0.93,
                "text": " sending."
            },
            {
                "category_id": 15,
                "poly": [
                    222.0,
                    1392.0,
                    394.0,
                    1392.0,
                    394.0,
                    1427.0,
                    222.0,
                    1427.0
                ],
                "score": 0.97,
                "text": ". .Not taken."
            },
            {
                "category_id": 15,
                "poly": [
                    2.0,
                    1722.0,
                    1138.0,
                    1722.0,
                    1138.0,
                    1751.0,
                    2.0,
                    1751.0
                ],
                "score": 0.99,
                "text": "d licensed use limited to: Everything Demo User. Downloaded on January 11,2024 at 15:55:37 UTC from IEEE Xplore. Restriction:"
            },
            {
                "category_id": 15,
                "poly": [
                    203.0,
                    193.0,
                    931.0,
                    193.0,
                    931.0,
                    226.0,
                    203.0,
                    226.0
                ],
                "score": 0.97,
                "text": "FIELD INTENSITY OF LAFAYETTE AND OF DISTURBANCES"
            },
            {
                "category_id": 15,
                "poly": [
                    493.0,
                    227.0,
                    970.0,
                    227.0,
                    970.0,
                    261.0,
                    493.0,
                    261.0
                ],
                "score": 0.94,
                "text": ")IN AUGUST,1923,IN M1CR0-V0LTS"
            },
            {
                "category_id": 15,
                "poly": [
                    489.0,
                    264.0,
                    639.0,
                    264.0,
                    639.0,
                    284.0,
                    489.0,
                    284.0
                ],
                "score": 0.72,
                "text": "nnnMTamnn"
            },
            {
                "category_id": 15,
                "poly": [
                    486.0,
                    259.0,
                    647.0,
                    259.0,
                    647.0,
                    294.0,
                    486.0,
                    294.0
                ],
                "score": 0.99,
                "text": "PER METER"
            },
            {
                "category_id": 15,
                "poly": [
                    203.0,
                    192.0,
                    931.0,
                    192.0,
                    931.0,
                    227.0,
                    203.0,
                    227.0
                ],
                "score": 0.99,
                "text": "FIELD INTENSITY OF LAFAYETTE AND OF DISTURBANCES"
            },
            {
                "category_id": 15,
                "poly": [
                    493.0,
                    228.0,
                    969.0,
                    228.0,
                    969.0,
                    261.0,
                    493.0,
                    261.0
                ],
                "score": 0.92,
                "text": ")IN AUGUST, 1923, IN M1CR0-VOLTS"
            },
            {
                "category_id": 15,
                "poly": [
                    488.0,
                    264.0,
                    644.0,
                    264.0,
                    644.0,
                    290.0,
                    488.0,
                    290.0
                ],
                "score": 0.85,
                "text": "PERMTTER"
            }
        ],
        "page_info": {
            "page_no": 4,
            "height": 1800,
            "width": 1134
        }
    },
    {
        "layout_dets": [
            {
                "category_id": 2,
                "poly": [
                    5.585905075073242,
                    1719.954345703125,
                    1134.0,
                    1719.954345703125,
                    1134.0,
                    1746.1990966796875,
                    5.585905075073242,
                    1746.1990966796875
                ],
                "score": 0.9997953176498413
            },
            {
                "category_id": 6,
                "poly": [
                    406.34869384765625,
                    242.2501678466797,
                    736.5595092773438,
                    242.2501678466797,
                    736.5595092773438,
                    275.5243835449219,
                    406.34869384765625,
                    275.5243835449219
                ],
                "score": 0.999589204788208
            },
            {
                "category_id": 5,
                "poly": [
                    166.55227661132812,
                    291.5498962402344,
                    970.9496459960938,
                    291.5498962402344,
                    970.9496459960938,
                    730.9144897460938,
                    166.55227661132812,
                    730.9144897460938
                ],
                "score": 0.9995543956756592
            },
            {
                "category_id": 1,
                "poly": [
                    594.7868041992188,
                    756.4357299804688,
                    940.0239868164062,
                    756.4357299804688,
                    940.0239868164062,
                    858.9746704101562,
                    594.7868041992188,
                    858.9746704101562
                ],
                "score": 0.9780656695365906
            },
            {
                "category_id": 1,
                "poly": [
                    163.7977752685547,
                    871.8240966796875,
                    971.18701171875,
                    871.8240966796875,
                    971.18701171875,
                    946.3713989257812,
                    163.7977752685547,
                    946.3713989257812
                ],
                "score": 0.5723991394042969
            },
            {
                "category_id": 7,
                "poly": [
                    163.36618041992188,
                    872.143310546875,
                    970.7710571289062,
                    872.143310546875,
                    970.7710571289062,
                    946.3195190429688,
                    163.36618041992188,
                    946.3195190429688
                ],
                "score": 0.3290655314922333
            },
            {
                "category_id": 7,
                "poly": [
                    594.6603393554688,
                    756.8045654296875,
                    940.8950805664062,
                    756.8045654296875,
                    940.8950805664062,
                    859.0047607421875,
                    594.6603393554688,
                    859.0047607421875
                ],
                "score": 0.23801051080226898
            },
            {
                "category_id": 15,
                "poly": [
                    1.0,
                    1722.0,
                    1138.0,
                    1722.0,
                    1138.0,
                    1751.0,
                    1.0,
                    1751.0
                ],
                "score": 1.0,
                "text": "ed licensed use limited to: Everything Demo User. Downloaded on January 11,2024 at 15:55:37 UTC from IEEE Xplore. Restriction:"
            },
            {
                "category_id": 15,
                "poly": [
                    405.0,
                    243.0,
                    734.0,
                    243.0,
                    734.0,
                    275.0,
                    405.0,
                    275.0
                ],
                "score": 0.98,
                "text": "RATIO OF AVERAGES"
            },
            {
                "category_id": 15,
                "poly": [
                    598.0,
                    755.0,
                    940.0,
                    755.0,
                    940.0,
                    795.0,
                    598.0,
                    795.0
                ],
                "score": 1.0,
                "text": "Radio Physical Laboratory,"
            },
            {
                "category_id": 15,
                "poly": [
                    596.0,
                    790.0,
                    872.0,
                    790.0,
                    872.0,
                    826.0,
                    596.0,
                    826.0
                ],
                "score": 0.98,
                "text": "Bureau of Standards,"
            },
            {
                "category_id": 15,
                "poly": [
                    597.0,
                    827.0,
                    859.0,
                    827.0,
                    859.0,
                    861.0,
                    597.0,
                    861.0
                ],
                "score": 0.99,
                "text": "September 25, 1923."
            },
            {
                "category_id": 15,
                "poly": [
                    164.0,
                    873.0,
                    968.0,
                    873.0,
                    968.0,
                    903.0,
                    164.0,
                    903.0
                ],
                "score": 0.99,
                "text": "SUMMARY: The signal strengths of the Nauen and Lafayette Stations,"
            },
            {
                "category_id": 15,
                "poly": [
                    165.0,
                    898.0,
                    967.0,
                    898.0,
                    967.0,
                    925.0,
                    165.0,
                    925.0
                ],
                "score": 0.98,
                "text": "and the corresponding strength of the atmospheric disturbances in Washing-"
            },
            {
                "category_id": 15,
                "poly": [
                    164.0,
                    919.0,
                    585.0,
                    919.0,
                    585.0,
                    948.0,
                    164.0,
                    948.0
                ],
                "score": 0.98,
                "text": "ton are given for July and August, 1923."
            },
            {
                "category_id": 15,
                "poly": [
                    163.0,
                    872.0,
                    969.0,
                    872.0,
                    969.0,
                    904.0,
                    163.0,
                    904.0
                ],
                "score": 0.99,
                "text": "SUMMARY: The signal strengths of the Nauen and Lafayette Stations,"
            },
            {
                "category_id": 15,
                "poly": [
                    165.0,
                    898.0,
                    967.0,
                    898.0,
                    967.0,
                    925.0,
                    165.0,
                    925.0
                ],
                "score": 0.98,
                "text": "and the corresponding strength of the atmospheric disturbances in Washing-"
            },
            {
                "category_id": 15,
                "poly": [
                    164.0,
                    920.0,
                    585.0,
                    920.0,
                    585.0,
                    948.0,
                    164.0,
                    948.0
                ],
                "score": 0.97,
                "text": "ton are given for July and August, 1923."
            },
            {
                "category_id": 15,
                "poly": [
                    598.0,
                    756.0,
                    940.0,
                    756.0,
                    940.0,
                    794.0,
                    598.0,
                    794.0
                ],
                "score": 1.0,
                "text": "Radio Physical Laboratory,"
            },
            {
                "category_id": 15,
                "poly": [
                    597.0,
                    792.0,
                    871.0,
                    792.0,
                    871.0,
                    824.0,
                    597.0,
                    824.0
                ],
                "score": 0.99,
                "text": "Bureau of Standards,"
            },
            {
                "category_id": 15,
                "poly": [
                    597.0,
                    827.0,
                    860.0,
                    827.0,
                    860.0,
                    860.0,
                    597.0,
                    860.0
                ],
                "score": 0.96,
                "text": "September 25, 1923."
            }
        ],
        "page_info": {
            "page_no": 5,
            "height": 1800,
            "width": 1134
        }
    }
]